ml_utils/Utils.py
ml_utils/__init__.py
ml_utils/augment_images.py
ml_utils/batch.py
ml_utils/bb_accuracy.py
ml_utils/bb_results.py
ml_utils/caffe_python_layers.py
ml_utils/caffe_utils.py
ml_utils/caffemodel_to_json.py
ml_utils/constants.py
ml_utils/conversion_utils.py
ml_utils/cpu_count.py
ml_utils/create_nn_imagelsts.py
ml_utils/darknet_convert.py
ml_utils/fcn_pixlevel_output_converter.py
ml_utils/hsv_util.py
ml_utils/imutils.py
ml_utils/interactive_grabcut.py
ml_utils/mnist_example.py
ml_utils/multilabel_accuracy.py
ml_utils/progress_plot.py
ml_utils/read_various_training_formats.py
ml_utils/solve_jr.py
ml_utils/tensorflow_tests.py
ml_utils/track.py
ml_utils/test/__init__.py
nn_utils/Utils.py
nn_utils/__init__.py
nn_utils/augment_images.py
nn_utils/batch.py
nn_utils/bb_accuracy.py
nn_utils/bb_results.py
nn_utils/caffe_python_layers.py
nn_utils/caffe_utils.py
nn_utils/caffemodel_to_json.py
nn_utils/constants.py
nn_utils/conversion_utils.py
nn_utils/cpu_count.py
nn_utils/create_nn_imagelsts.py
nn_utils/darknet_convert.py
nn_utils/fcn_pixlevel_output_converter.py
nn_utils/hsv_util.py
nn_utils/imutils.py
nn_utils/interactive_grabcut.py
nn_utils/mnist_example.py
nn_utils/multilabel_accuracy.py
nn_utils/progress_plot.py
nn_utils/read_various_training_formats.py
nn_utils/solve_jr.py
nn_utils/tensorflow_tests.py
nn_utils/track.py
nn_utils/test/__init__.py
nn_utils-0.1.0.dist-info/DESCRIPTION.rst
nn_utils-0.1.0.dist-info/METADATA
nn_utils-0.1.0.dist-info/RECORD
nn_utils-0.1.0.dist-info/WHEEL
nn_utils-0.1.0.dist-info/metadata.json
nn_utils-0.1.0.dist-info/top_level.txt
