Metadata-Version: 2.0
Name: nn-utils
Version: 0.1.0
Summary: Useful machine-learning related stuff.
Home-page: https://github.com/jeremy-rutman/ml-support-code-in-python
Author: Jeremy Rutman
Author-email: jeremy.rutman@gmail.com
License: LICENSE.txt
Keywords: neural networks support code
Platform: UNKNOWN
Classifier: Development Status :: 4 - Beta
Classifier: Intended Audience :: Developers
Classifier: Topic :: Software Development :: Build Tools
Classifier: License :: OSI Approved :: MIT License
Classifier: Programming Language :: Python :: 2.7
Classifier: Programming Language :: Python :: 3
Requires-Dist: numpy (>=0.1.4)
